ngmaster/__init__.py
ngmaster/run_ngmaster.py
ngmaster/run_ngmaster_2.py
ngmaster/utils.py
ngmaster/utils_2.py
ngmaster/utils_logger.py
ngmaster/db/blast/mlst.fa
ngmaster/db/blast/mlst.fa.ndb
ngmaster/db/blast/mlst.fa.nhd
ngmaster/db/blast/mlst.fa.nhi
ngmaster/db/blast/mlst.fa.nhr
ngmaster/db/blast/mlst.fa.nin
ngmaster/db/blast/mlst.fa.njs
ngmaster/db/blast/mlst.fa.nog
ngmaster/db/blast/mlst.fa.nos
ngmaster/db/blast/mlst.fa.not
ngmaster/db/blast/mlst.fa.nsq
ngmaster/db/blast/mlst.fa.ntf
ngmaster/db/blast/mlst.fa.nto
ngmaster/db/pubmlst/ngmast/ngmast.txt
ngmaster/db/pubmlst/ngmast/porB.tfa
ngmaster/db/pubmlst/ngmast/tbpB.tfa
ngmaster/db/pubmlst/ngstar/23S.tfa
ngmaster/db/pubmlst/ngstar/allele_comments.tsv
ngmaster/db/pubmlst/ngstar/gyrA.tfa
ngmaster/db/pubmlst/ngstar/mtrR.tfa
ngmaster/db/pubmlst/ngstar/ngstar.txt
ngmaster/db/pubmlst/ngstar/parC.tfa
ngmaster/db/pubmlst/ngstar/penA.tfa
ngmaster/db/pubmlst/ngstar/ponA.tfa
ngmaster/db/pubmlst/ngstar/porB.tfa
ngmaster/scripts/mlst-make_blast_db
ngmaster/test/COPYING
ngmaster/test/COPYING.LESSER
ngmaster/test/assert.sh
ngmaster/test/noseq.fa
ngmaster/test/null.fa
ngmaster/test/test.fa
ngmaster-1.1.1.dist-info/LICENSE
ngmaster-1.1.1.dist-info/METADATA
ngmaster-1.1.1.dist-info/WHEEL
ngmaster-1.1.1.dist-info/entry_points.txt
ngmaster-1.1.1.dist-info/top_level.txt
ngmaster-1.1.1.dist-info/RECORD
