Metadata-Version: 2.1
Name: ngmaster
Version: 1.1.1
Summary: In silico multi-antigen sequence typing for Neisseria gonorrhoeae (NG-MAST)
Home-page: https://github.com/MDU-PHL/ngmaster
Author: Jason Kwong
Author-email: kwongj@gmail.com
License: GPLv3
Keywords: microbial genomics Neisseria sequence typing
Classifier: Development Status :: 4 - Beta
Classifier: License :: OSI Approved :: GNU General Public License v3 (GPLv3)
Classifier: Programming Language :: Python :: 3.6
Classifier: Programming Language :: Python :: 3.7
Classifier: Programming Language :: Python :: 3.8
Classifier: Programming Language :: Python :: 3.9
Classifier: Topic :: Scientific/Engineering :: Bio-Informatics
Classifier: Topic :: Scientific/Engineering :: Medical Science Apps.
Classifier: Intended Audience :: Science/Research
Requires-Python: >=3.6
License-File: LICENSE
Requires-Dist: argparse
Requires-Dist: biopython
Requires-Dist: bs4
Requires-Dist: requests
